{"stats":{"minecraft:dropped":{"minecraft:dispenser":1},"minecraft:used":{"minecraft:gray_carpet":18,"minecraft:brown_carpet":1,"minecraft:white_stained_glass":5},"minecraft:picked_up":{"minecraft:dispenser":1},"minecraft:custom":{"minecraft:jump":18,"minecraft:time_since_rest":11349769,"minecraft:damage_taken":1260,"minecraft:minecart_one_cm":2650,"minecraft:play_one_minute":21196543,"minecraft:crouch_one_cm":1098,"minecraft:leave_game":216,"minecraft:time_since_death":11349748,"minecraft:sprint_one_cm":2292,"minecraft:walk_one_cm":4755,"minecraft:walk_on_water_one_cm":283178,"minecraft:deaths":5,"minecraft:sneak_time":147889,"minecraft:walk_under_water_one_cm":763631,"minecraft:fall_one_cm":962,"minecraft:drop":1,"minecraft:fly_one_cm":114746602}},"DataVersion":2567}